{"pageId":"/src/pages/posts/@id","routeParams":{"id":"1qmkg9f"},"data":{"post":{"date":1769351133000,"reddit":"https://www.reddit.com/r/touhou/comments/1qmkg9f","url":["https://i.redd.it/fuqy2gha9ifg1.png"],"src":"https://x.com/Shameimarulike/status/2015379129949126829","desc":"Miracle mallet taking a day off today.","artistId":"gurajio","characterIds":["ichirin","futo"],"nsfw":false},"artist":{"id":"gurajio","name":"ぐらじお","linkTwitter":"https://x.com/Shameimarulike","portrait":"portraits/placeholders/spy.webp","artworkCount":3,"characterCount":2},"characters":[{"id":"ichirin","name":"Kumoi Ichirin","short_name":"Ichirin","work":["ufo"],"portrait":"portraits/characters/ichirin.webp","artworkCount":12,"artistCount":11},{"id":"futo","name":"Mononobe no Futo","short_name":"Futo","work":["td"],"portrait":"portraits/characters/futo.webp","artworkCount":30,"artistCount":24}],"randomArtistPosts":[{"id":"1nobihl","img":"https://i.redd.it/ellhn1o9gvqf1.png","nsfw":false},{"id":"1j112a9","img":"https://i.redd.it/xfrg2hnjc3me1.png","nsfw":false}],"prevPostId":"1qmgzqe","nextPostId":"1qml0yx"}}