{
  "_chunk-BITFmjU1.js": {
    "file": "assets/chunks/chunk-BITFmjU1.js",
    "name": "Loading",
    "imports": [
      "_chunk-Cv7W3xNm.js"
    ],
    "dynamicImports": [
      "data/posts/posts-2024.json",
      "data/posts/posts-2025.json",
      "data/artists.json",
      "data/characters.json"
    ],
    "css": [
      "assets/static/vike-react-9c9f96f4.BcWtY8Ol.css"
    ]
  },
  "_chunk-BQK9ezv8.js": {
    "file": "assets/chunks/chunk-BQK9ezv8.js",
    "name": "Button",
    "imports": [
      "_chunk-BITFmjU1.js"
    ]
  },
  "_chunk-BXpfnjVt.js": {
    "file": "assets/chunks/chunk-BXpfnjVt.js",
    "name": "useFormControl",
    "imports": [
      "_chunk-BITFmjU1.js"
    ]
  },
  "_chunk-CQ0bSu_Q.js": {
    "file": "assets/chunks/chunk-CQ0bSu_Q.js",
    "name": "TextField",
    "imports": [
      "_chunk-BITFmjU1.js",
      "_chunk-BXpfnjVt.js",
      "_chunk-CeTJ7EVW.js",
      "_chunk-Jq1wfNm4.js"
    ]
  },
  "_chunk-CeTJ7EVW.js": {
    "file": "assets/chunks/chunk-CeTJ7EVW.js",
    "name": "Grow",
    "imports": [
      "_chunk-BITFmjU1.js"
    ]
  },
  "_chunk-Cv7W3xNm.js": {
    "file": "assets/chunks/chunk-Cv7W3xNm.js",
    "name": "preload-helper"
  },
  "_chunk-DNyHRjt3.js": {
    "file": "assets/chunks/chunk-DNyHRjt3.js",
    "name": "Tooltip",
    "imports": [
      "_chunk-BITFmjU1.js",
      "_chunk-CeTJ7EVW.js"
    ]
  },
  "_chunk-DfpT5f-D.js": {
    "file": "assets/chunks/chunk-DfpT5f-D.js",
    "name": "index",
    "imports": [
      "_chunk-BITFmjU1.js"
    ]
  },
  "_chunk-Jq1wfNm4.js": {
    "file": "assets/chunks/chunk-Jq1wfNm4.js",
    "name": "mergeSlotProps",
    "imports": [
      "_chunk-BITFmjU1.js"
    ]
  },
  "_chunk-OF3yPMkr.js": {
    "file": "assets/chunks/chunk-OF3yPMkr.js",
    "name": "ProfileItem",
    "imports": [
      "_chunk-BITFmjU1.js",
      "_chunk-DfpT5f-D.js"
    ]
  },
  "_chunk-Ofy8F7iq.js": {
    "file": "assets/chunks/chunk-Ofy8F7iq.js",
    "name": "ListPage",
    "imports": [
      "_chunk-BITFmjU1.js",
      "_chunk-OF3yPMkr.js",
      "_chunk-DNyHRjt3.js",
      "_chunk-CQ0bSu_Q.js"
    ]
  },
  "_vike-react-9c9f96f4.BcWtY8Ol.css": {
    "file": "assets/static/vike-react-9c9f96f4.BcWtY8Ol.css",
    "src": "_vike-react-9c9f96f4.BcWtY8Ol.css"
  },
  "data/artists.json": {
    "file": "assets/chunks/chunk-66Ch_Lgo.js",
    "name": "artists",
    "src": "data/artists.json",
    "isDynamicEntry": true
  },
  "data/characters.json": {
    "file": "assets/chunks/chunk-Cxqb0P6m.js",
    "name": "characters",
    "src": "data/characters.json",
    "isDynamicEntry": true
  },
  "data/posts/posts-2024.json": {
    "file": "assets/chunks/chunk-BeqdQL10.js",
    "name": "posts-2024",
    "src": "data/posts/posts-2024.json",
    "isDynamicEntry": true
  },
  "data/posts/posts-2025.json": {
    "file": "assets/chunks/chunk-7aka6rMx.js",
    "name": "posts-2025",
    "src": "data/posts/posts-2025.json",
    "isDynamicEntry": true
  },
  "node_modules/vike/dist/esm/client/runtime-client-routing/entry.js": {
    "file": "assets/entries/entry-client-routing.C4Xyu4z6.js",
    "name": "entries/entry-client-routing",
    "src": "node_modules/vike/dist/esm/client/runtime-client-routing/entry.js",
    "isEntry": true,
    "imports": [
      "_chunk-Cv7W3xNm.js"
    ],
    "dynamicImports": [
      "virtual:vike:page-entry:client:/src/pages/_error",
      "virtual:vike:page-entry:client:/src/pages/admin",
      "virtual:vike:page-entry:client:/src/pages/artists",
      "virtual:vike:page-entry:client:/src/pages/characters",
      "virtual:vike:page-entry:client:/src/pages/gallery",
      "virtual:vike:page-entry:client:/src/pages/index",
      "virtual:vike:page-entry:client:/src/pages/posts/@id"
    ]
  },
  "virtual:vike:page-entry:client:/src/pages/_error": {
    "file": "assets/entries/src_pages_error.DLRANl0L.js",
    "name": "entries/src/pages/_error",
    "src": "virtual:vike:page-entry:client:/src/pages/_error",
    "isEntry": true,
    "isDynamicEntry": true,
    "imports": [
      "_chunk-BITFmjU1.js",
      "_chunk-Cv7W3xNm.js"
    ],
    "css": [
      "assets/static/vike-react-9c9f96f4.BcWtY8Ol.css"
    ]
  },
  "virtual:vike:page-entry:client:/src/pages/admin": {
    "file": "assets/entries/src_pages_admin.Cvc_4vvp.js",
    "name": "entries/src/pages/admin",
    "src": "virtual:vike:page-entry:client:/src/pages/admin",
    "isEntry": true,
    "isDynamicEntry": true,
    "imports": [
      "_chunk-BITFmjU1.js",
      "data/artists.json",
      "data/characters.json",
      "_chunk-CQ0bSu_Q.js",
      "_chunk-CeTJ7EVW.js",
      "_chunk-BQK9ezv8.js",
      "_chunk-Cv7W3xNm.js",
      "_chunk-BXpfnjVt.js",
      "_chunk-Jq1wfNm4.js"
    ],
    "css": [
      "assets/static/vike-react-9c9f96f4.BcWtY8Ol.css"
    ]
  },
  "virtual:vike:page-entry:client:/src/pages/artists": {
    "file": "assets/entries/src_pages_artists.jfejgbUm.js",
    "name": "entries/src/pages/artists",
    "src": "virtual:vike:page-entry:client:/src/pages/artists",
    "isEntry": true,
    "isDynamicEntry": true,
    "imports": [
      "_chunk-BITFmjU1.js",
      "_chunk-DfpT5f-D.js",
      "_chunk-Ofy8F7iq.js",
      "_chunk-Cv7W3xNm.js",
      "_chunk-OF3yPMkr.js",
      "_chunk-DNyHRjt3.js",
      "_chunk-CeTJ7EVW.js",
      "_chunk-CQ0bSu_Q.js",
      "_chunk-BXpfnjVt.js",
      "_chunk-Jq1wfNm4.js"
    ],
    "css": [
      "assets/static/vike-react-9c9f96f4.BcWtY8Ol.css"
    ]
  },
  "virtual:vike:page-entry:client:/src/pages/characters": {
    "file": "assets/entries/src_pages_characters.nesgqql9.js",
    "name": "entries/src/pages/characters",
    "src": "virtual:vike:page-entry:client:/src/pages/characters",
    "isEntry": true,
    "isDynamicEntry": true,
    "imports": [
      "_chunk-BITFmjU1.js",
      "_chunk-DfpT5f-D.js",
      "_chunk-Ofy8F7iq.js",
      "_chunk-Cv7W3xNm.js",
      "_chunk-OF3yPMkr.js",
      "_chunk-DNyHRjt3.js",
      "_chunk-CeTJ7EVW.js",
      "_chunk-CQ0bSu_Q.js",
      "_chunk-BXpfnjVt.js",
      "_chunk-Jq1wfNm4.js"
    ],
    "css": [
      "assets/static/vike-react-9c9f96f4.BcWtY8Ol.css"
    ]
  },
  "virtual:vike:page-entry:client:/src/pages/gallery": {
    "file": "assets/entries/src_pages_gallery.Df7LhCBW.js",
    "name": "entries/src/pages/gallery",
    "src": "virtual:vike:page-entry:client:/src/pages/gallery",
    "isEntry": true,
    "isDynamicEntry": true,
    "imports": [
      "_chunk-BITFmjU1.js",
      "_chunk-DfpT5f-D.js",
      "_chunk-OF3yPMkr.js",
      "_chunk-DNyHRjt3.js",
      "_chunk-BXpfnjVt.js",
      "_chunk-CeTJ7EVW.js",
      "_chunk-Cv7W3xNm.js"
    ],
    "css": [
      "assets/static/vike-react-9c9f96f4.BcWtY8Ol.css"
    ]
  },
  "virtual:vike:page-entry:client:/src/pages/index": {
    "file": "assets/entries/src_pages_index.DjZTEolb.js",
    "name": "entries/src/pages/index",
    "src": "virtual:vike:page-entry:client:/src/pages/index",
    "isEntry": true,
    "isDynamicEntry": true,
    "imports": [
      "_chunk-BITFmjU1.js",
      "_chunk-DfpT5f-D.js",
      "_chunk-Cv7W3xNm.js"
    ],
    "css": [
      "assets/static/vike-react-9c9f96f4.BcWtY8Ol.css"
    ]
  },
  "virtual:vike:page-entry:client:/src/pages/posts/@id": {
    "file": "assets/entries/src_pages_posts_-id.BScSRLuU.js",
    "name": "entries/src/pages/posts/@id",
    "src": "virtual:vike:page-entry:client:/src/pages/posts/@id",
    "isEntry": true,
    "isDynamicEntry": true,
    "imports": [
      "_chunk-BITFmjU1.js",
      "_chunk-DfpT5f-D.js",
      "_chunk-CeTJ7EVW.js",
      "_chunk-Jq1wfNm4.js",
      "_chunk-DNyHRjt3.js",
      "_chunk-BQK9ezv8.js",
      "_chunk-Cv7W3xNm.js"
    ],
    "css": [
      "assets/static/vike-react-9c9f96f4.BcWtY8Ol.css"
    ]
  }
}