{
  "_chunk-1vZWPLyC.js": {
    "file": "assets/chunks/chunk-1vZWPLyC.js",
    "name": "Container",
    "imports": [
      "_chunk-Dy9C_Ocf.js",
      "_chunk-CAmVzbS8.js"
    ]
  },
  "_chunk-BEEy94aN.js": {
    "file": "assets/chunks/chunk-BEEy94aN.js",
    "name": "TextField",
    "imports": [
      "_chunk-Dy9C_Ocf.js",
      "_chunk-C-nr1p1w.js",
      "_chunk-B_ah4L4C.js",
      "_chunk-DgPrC-IC.js",
      "_chunk-Ls7yMqxa.js"
    ]
  },
  "_chunk-B_ah4L4C.js": {
    "file": "assets/chunks/chunk-B_ah4L4C.js",
    "name": "useFormControl",
    "imports": [
      "_chunk-Dy9C_Ocf.js"
    ]
  },
  "_chunk-BggHBmtZ.js": {
    "file": "assets/chunks/chunk-BggHBmtZ.js",
    "name": "navigate",
    "imports": [
      "_chunk-BrhNgn6_.js"
    ]
  },
  "_chunk-BhM667Ry.js": {
    "file": "assets/chunks/chunk-BhM667Ry.js",
    "name": "getThemeProps",
    "imports": [
      "_chunk-Dy9C_Ocf.js"
    ]
  },
  "_chunk-BrhNgn6_.js": {
    "file": "assets/chunks/chunk-BrhNgn6_.js",
    "name": "renderPageClientSide",
    "imports": [
      "_chunk-PSOkAIay.js"
    ],
    "dynamicImports": [
      "virtual:vike:pageConfigLazy:client:/src/pages/admin",
      "virtual:vike:pageConfigLazy:client:/src/pages/artists",
      "virtual:vike:pageConfigLazy:client:/src/pages/characters",
      "virtual:vike:pageConfigLazy:client:/src/pages/gallery",
      "virtual:vike:pageConfigLazy:client:/src/pages/index",
      "virtual:vike:pageConfigLazy:client:/src/pages/posts/@id"
    ]
  },
  "_chunk-C-nr1p1w.js": {
    "file": "assets/chunks/chunk-C-nr1p1w.js",
    "name": "ButtonBase",
    "imports": [
      "_chunk-Dy9C_Ocf.js",
      "_chunk-Ls7yMqxa.js"
    ]
  },
  "_chunk-CAmVzbS8.js": {
    "file": "assets/chunks/chunk-CAmVzbS8.js",
    "name": "useThemeProps",
    "imports": [
      "_chunk-Dy9C_Ocf.js",
      "_chunk-BhM667Ry.js"
    ]
  },
  "_chunk-CD-UgIlD.js": {
    "file": "assets/chunks/chunk-CD-UgIlD.js",
    "name": "Stack",
    "imports": [
      "_chunk-Dy9C_Ocf.js",
      "_chunk-CAmVzbS8.js"
    ]
  },
  "_chunk-DDKZcktH.js": {
    "file": "assets/chunks/chunk-DDKZcktH.js",
    "name": "ListPage",
    "imports": [
      "_chunk-Dy9C_Ocf.js",
      "_chunk-KxMjz5_k.js",
      "_chunk-C-nr1p1w.js",
      "_chunk-Ls7yMqxa.js",
      "_chunk-B_ah4L4C.js",
      "_chunk-DgPrC-IC.js",
      "_chunk-BEEy94aN.js",
      "_chunk-S-fRVKVV.js",
      "_chunk-1vZWPLyC.js"
    ]
  },
  "_chunk-DMjb9ISz.js": {
    "file": "assets/chunks/chunk-DMjb9ISz.js",
    "name": "Link",
    "imports": [
      "_chunk-Dy9C_Ocf.js",
      "_chunk-Ls7yMqxa.js"
    ]
  },
  "_chunk-DgPrC-IC.js": {
    "file": "assets/chunks/chunk-DgPrC-IC.js",
    "name": "List",
    "imports": [
      "_chunk-Dy9C_Ocf.js",
      "_chunk-C-nr1p1w.js",
      "_chunk-pu0H1ned.js",
      "_chunk-Ls7yMqxa.js"
    ]
  },
  "_chunk-Dy9C_Ocf.js": {
    "file": "assets/chunks/chunk-Dy9C_Ocf.js",
    "name": "_onRenderClient",
    "imports": [
      "_chunk-PSOkAIay.js"
    ],
    "dynamicImports": [
      "src/components/Navbar/Navbar.tsx",
      "src/components/Footer/Footer.tsx"
    ],
    "css": [
      "assets/static/src_renderer_index-54ec5530.BBfZVkUH.css"
    ]
  },
  "_chunk-KxMjz5_k.js": {
    "file": "assets/chunks/chunk-KxMjz5_k.js",
    "name": "ProfileItem",
    "imports": [
      "_chunk-Dy9C_Ocf.js",
      "_chunk-BggHBmtZ.js",
      "_chunk-BrhNgn6_.js",
      "_chunk-C-nr1p1w.js"
    ]
  },
  "_chunk-Ls7yMqxa.js": {
    "file": "assets/chunks/chunk-Ls7yMqxa.js",
    "name": "isFocusVisible",
    "imports": [
      "_chunk-Dy9C_Ocf.js"
    ]
  },
  "_chunk-PSOkAIay.js": {
    "file": "assets/chunks/chunk-PSOkAIay.js",
    "name": "preload-helper"
  },
  "_chunk-S-fRVKVV.js": {
    "file": "assets/chunks/chunk-S-fRVKVV.js",
    "name": "IconButton",
    "imports": [
      "_chunk-Dy9C_Ocf.js",
      "_chunk-C-nr1p1w.js"
    ]
  },
  "_chunk-_MjiKTlx.js": {
    "file": "assets/chunks/chunk-_MjiKTlx.js",
    "name": "extractRedditId"
  },
  "_chunk-pu0H1ned.js": {
    "file": "assets/chunks/chunk-pu0H1ned.js",
    "name": "index",
    "imports": [
      "_chunk-Dy9C_Ocf.js"
    ]
  },
  "_src_renderer_index-54ec5530.BBfZVkUH.css": {
    "file": "assets/static/src_renderer_index-54ec5530.BBfZVkUH.css",
    "src": "_src_renderer_index-54ec5530.BBfZVkUH.css"
  },
  "node_modules/vike/dist/esm/client/runtime-client-routing/entry.js": {
    "file": "assets/entries/entry-client-routing.GANOiT1x.js",
    "name": "entries/entry-client-routing",
    "src": "node_modules/vike/dist/esm/client/runtime-client-routing/entry.js",
    "isEntry": true,
    "imports": [
      "_chunk-BrhNgn6_.js",
      "_chunk-PSOkAIay.js"
    ]
  },
  "src/components/Footer/Footer.tsx": {
    "file": "assets/chunks/chunk-Dw13b_Or.js",
    "name": "Footer",
    "src": "src/components/Footer/Footer.tsx",
    "isDynamicEntry": true,
    "imports": [
      "_chunk-Dy9C_Ocf.js",
      "_chunk-DMjb9ISz.js",
      "_chunk-1vZWPLyC.js",
      "_chunk-CD-UgIlD.js",
      "_chunk-PSOkAIay.js",
      "_chunk-Ls7yMqxa.js",
      "_chunk-CAmVzbS8.js",
      "_chunk-BhM667Ry.js"
    ],
    "css": [
      "assets/static/src_renderer_index-54ec5530.BBfZVkUH.css"
    ]
  },
  "src/components/Navbar/Navbar.tsx": {
    "file": "assets/chunks/chunk-8Ft5eHyx.js",
    "name": "Navbar",
    "src": "src/components/Navbar/Navbar.tsx",
    "isDynamicEntry": true,
    "imports": [
      "_chunk-Dy9C_Ocf.js",
      "_chunk-BggHBmtZ.js",
      "_chunk-BrhNgn6_.js",
      "_chunk-_MjiKTlx.js",
      "_chunk-C-nr1p1w.js",
      "_chunk-Ls7yMqxa.js",
      "_chunk-BhM667Ry.js",
      "_chunk-S-fRVKVV.js",
      "_chunk-DgPrC-IC.js",
      "_chunk-PSOkAIay.js",
      "_chunk-pu0H1ned.js"
    ],
    "css": [
      "assets/static/src_renderer_index-54ec5530.BBfZVkUH.css"
    ]
  },
  "virtual:vike:pageConfigLazy:client:/src/pages/admin": {
    "file": "assets/entries/src_pages_admin.Tx7052LG.js",
    "name": "entries/src/pages/admin",
    "src": "virtual:vike:pageConfigLazy:client:/src/pages/admin",
    "isEntry": true,
    "isDynamicEntry": true,
    "imports": [
      "_chunk-Dy9C_Ocf.js",
      "_chunk-C-nr1p1w.js",
      "_chunk-CD-UgIlD.js",
      "_chunk-BEEy94aN.js",
      "_chunk-Ls7yMqxa.js",
      "_chunk-B_ah4L4C.js",
      "_chunk-DgPrC-IC.js",
      "_chunk-PSOkAIay.js",
      "_chunk-CAmVzbS8.js",
      "_chunk-BhM667Ry.js",
      "_chunk-pu0H1ned.js"
    ],
    "css": [
      "assets/static/src_renderer_index-54ec5530.BBfZVkUH.css"
    ]
  },
  "virtual:vike:pageConfigLazy:client:/src/pages/artists": {
    "file": "assets/entries/src_pages_artists.1WdeAqcv.js",
    "name": "entries/src/pages/artists",
    "src": "virtual:vike:pageConfigLazy:client:/src/pages/artists",
    "isEntry": true,
    "isDynamicEntry": true,
    "imports": [
      "_chunk-Dy9C_Ocf.js",
      "_chunk-DDKZcktH.js",
      "_chunk-PSOkAIay.js",
      "_chunk-KxMjz5_k.js",
      "_chunk-BggHBmtZ.js",
      "_chunk-BrhNgn6_.js",
      "_chunk-C-nr1p1w.js",
      "_chunk-Ls7yMqxa.js",
      "_chunk-B_ah4L4C.js",
      "_chunk-DgPrC-IC.js",
      "_chunk-pu0H1ned.js",
      "_chunk-BEEy94aN.js",
      "_chunk-S-fRVKVV.js",
      "_chunk-1vZWPLyC.js",
      "_chunk-CAmVzbS8.js",
      "_chunk-BhM667Ry.js"
    ],
    "css": [
      "assets/static/src_renderer_index-54ec5530.BBfZVkUH.css"
    ]
  },
  "virtual:vike:pageConfigLazy:client:/src/pages/characters": {
    "file": "assets/entries/src_pages_characters.C0xAz_ao.js",
    "name": "entries/src/pages/characters",
    "src": "virtual:vike:pageConfigLazy:client:/src/pages/characters",
    "isEntry": true,
    "isDynamicEntry": true,
    "imports": [
      "_chunk-Dy9C_Ocf.js",
      "_chunk-DDKZcktH.js",
      "_chunk-PSOkAIay.js",
      "_chunk-KxMjz5_k.js",
      "_chunk-BggHBmtZ.js",
      "_chunk-BrhNgn6_.js",
      "_chunk-C-nr1p1w.js",
      "_chunk-Ls7yMqxa.js",
      "_chunk-B_ah4L4C.js",
      "_chunk-DgPrC-IC.js",
      "_chunk-pu0H1ned.js",
      "_chunk-BEEy94aN.js",
      "_chunk-S-fRVKVV.js",
      "_chunk-1vZWPLyC.js",
      "_chunk-CAmVzbS8.js",
      "_chunk-BhM667Ry.js"
    ],
    "css": [
      "assets/static/src_renderer_index-54ec5530.BBfZVkUH.css"
    ]
  },
  "virtual:vike:pageConfigLazy:client:/src/pages/gallery": {
    "file": "assets/entries/src_pages_gallery.BeBYWxJk.js",
    "name": "entries/src/pages/gallery",
    "src": "virtual:vike:pageConfigLazy:client:/src/pages/gallery",
    "isEntry": true,
    "isDynamicEntry": true,
    "imports": [
      "_chunk-Dy9C_Ocf.js",
      "_chunk-_MjiKTlx.js",
      "_chunk-KxMjz5_k.js",
      "_chunk-Ls7yMqxa.js",
      "_chunk-1vZWPLyC.js",
      "_chunk-CD-UgIlD.js",
      "_chunk-B_ah4L4C.js",
      "_chunk-C-nr1p1w.js",
      "_chunk-PSOkAIay.js",
      "_chunk-BggHBmtZ.js",
      "_chunk-BrhNgn6_.js",
      "_chunk-CAmVzbS8.js",
      "_chunk-BhM667Ry.js"
    ],
    "css": [
      "assets/static/src_renderer_index-54ec5530.BBfZVkUH.css"
    ]
  },
  "virtual:vike:pageConfigLazy:client:/src/pages/index": {
    "file": "assets/entries/src_pages_index.wnaFj94q.js",
    "name": "entries/src/pages/index",
    "src": "virtual:vike:pageConfigLazy:client:/src/pages/index",
    "isEntry": true,
    "isDynamicEntry": true,
    "imports": [
      "_chunk-Dy9C_Ocf.js",
      "_chunk-PSOkAIay.js"
    ],
    "css": [
      "assets/static/src_renderer_index-54ec5530.BBfZVkUH.css"
    ]
  },
  "virtual:vike:pageConfigLazy:client:/src/pages/posts/@id": {
    "file": "assets/entries/src_pages_posts_-id.Bkmw_tD0.js",
    "name": "entries/src/pages/posts/@id",
    "src": "virtual:vike:pageConfigLazy:client:/src/pages/posts/@id",
    "isEntry": true,
    "isDynamicEntry": true,
    "imports": [
      "_chunk-Dy9C_Ocf.js",
      "_chunk-_MjiKTlx.js",
      "_chunk-C-nr1p1w.js",
      "_chunk-DMjb9ISz.js",
      "_chunk-S-fRVKVV.js",
      "_chunk-pu0H1ned.js",
      "_chunk-KxMjz5_k.js",
      "_chunk-PSOkAIay.js",
      "_chunk-Ls7yMqxa.js",
      "_chunk-BggHBmtZ.js",
      "_chunk-BrhNgn6_.js"
    ],
    "css": [
      "assets/static/src_renderer_index-54ec5530.BBfZVkUH.css"
    ]
  }
}