{"pageId":"/src/pages/posts/@id","routeParams":{"id":"1bagxea"},"data":{"post":{"date":1709988265000,"reddit":"https://www.reddit.com/r/touhou/comments/1bagxea","url":["https://i.redd.it/s1g5f0hz0bnc1.png"],"src":"https://x.com/simerike5/status/1765679631196418127","desc":"If you can't beat her, adopt her.\n\nThe talisman says **Hakurei** (博麗), by the way.","artistId":"deetamu","characterIds":["reimu","sanae"],"nsfw":false},"artist":{"id":"deetamu","name":"で～たむ","linkTwitter":"https://x.com/simerike5","linkPixiv":"https://www.pixiv.net/en/users/3079181","portrait":"portraits/artists/deetamu.webp","artworkCount":63,"characterCount":31},"characters":[{"id":"reimu","name":"Hakurei Reimu","short_name":"Reimu","work":["eosd"],"portrait":"portraits/characters/reimu.webp","artworkCount":279,"artistCount":117},{"id":"sanae","name":"Kochiya Sanae","short_name":"Sanae","work":["mof","sa","ufo","soku","td","lolk","um","udoalg"],"portrait":"portraits/characters/sanae.webp","artworkCount":70,"artistCount":42}],"randomArtistPosts":[{"id":"1ax5fzj","img":"https://i.redd.it/75xtdca7t4kc1.png","nsfw":false},{"id":"1ftq7bi","img":"https://i.redd.it/db829z53t5sd1.png","nsfw":false},{"id":"1lsdbrp","img":"https://i.redd.it/nuuclcmcx2bf1.png","nsfw":false},{"id":"1pznk0s","img":"https://i.redd.it/y0oqbn2iidag1.png","nsfw":false}],"prevPostId":"1b9ol78","nextPostId":"1bb9ft5"}}