{"pageId":"/src/pages/posts/@id","routeParams":{"id":"1hr2cfd"},"data":{"post":{"date":1735735825000,"reddit":"https://www.reddit.com/r/touhou/comments/1hr2cfd","url":["https://i.redd.it/jxlmnhnqpdae1.png"],"src":"https://x.com/campagne_9/status/1868670255092097091","desc":"Yeah, mackerel to tengu is like garlic to vampires.\n\nSo in the myths, tengu kidnap children. However, if you yell out \"I eat mackerel!\", then they will ignore you – hence, \"tengu hate mackerel\". But as far as I could look up, this seems to be a more modern invention?","artistId":"kanpa","characterIds":["aya","reimu","marisa"],"nsfw":false},"artist":{"id":"kanpa","name":"カンパ","linkTwitter":"https://x.com/campagne_9","linkPixiv":"https://www.pixiv.net/en/users/2520952","portrait":"portraits/artists/kanpa.webp","artworkCount":19,"characterCount":21},"characters":[{"id":"reimu","name":"Hakurei Reimu","short_name":"Reimu","work":["eosd"],"portrait":"portraits/characters/reimu.webp","artworkCount":279,"artistCount":117},{"id":"marisa","name":"Kirisame Marisa","short_name":"Marisa","work":["eosd"],"portrait":"portraits/characters/marisa.webp","artworkCount":163,"artistCount":76},{"id":"aya","name":"Shameimaru Aya","short_name":"Aya","work":["pofv","sa","mof","ds"],"portrait":"portraits/characters/aya.webp","artworkCount":71,"artistCount":34}],"randomArtistPosts":[{"id":"1kosi7t","img":"https://i.redd.it/wtf6ccd4cc1f1.png","nsfw":false},{"id":"1jfo9yd","img":"https://i.redd.it/nmbn4q2ydupe1.png","nsfw":false},{"id":"1l0o8pf","img":"https://i.redd.it/x6gkzshtbb4f1.png","nsfw":false},{"id":"1lywred","img":"https://i.redd.it/xt6iml5j2ocf1.png","nsfw":false}],"prevPostId":"1hqgla8","nextPostId":"1hr3owg"}}