{"_urlRewrite":null,"pageId":"/src/pages/posts/@id","routeParams":{"id":"1pi1wta"},"data":{"post":{"date":1765267346000,"reddit":"https://www.reddit.com/r/touhou/comments/1pi1wta","url":["https://i.redd.it/metylmo4y46g1.png"],"src":"https://x.com/mati10110302/status/1997638595054600602","desc":"# The hell you mean Reimu's real name is Ib? 🤨","artistId":"machi_paterina","characterIds":["marisa"],"nsfw":false},"artist":{"id":"machi_paterina","name":"まちぱてりーな","linkTwitter":"https://x.com/mati100311","portrait":"portraits/artists/machi_paterina.webp","artworkCount":22,"characterCount":6},"characters":[{"id":"marisa","name":"Kirisame Marisa","short_name":"Marisa","work":["eosd"],"portrait":"portraits/characters/marisa.webp","artworkCount":153,"artistCount":73}],"randomArtistPosts":[{"id":"1mzkhp9","img":"https://i.redd.it/hznnoft8h4lf1.png","nsfw":false},{"id":"1mbaa3k","img":"https://i.redd.it/rlf8vy8snkff1.png","nsfw":false},{"id":"1jlxeig","img":"https://i.redd.it/92rh3sgu5gre1.png","nsfw":false},{"id":"1jv4yfg","img":"https://i.redd.it/8v0yixmr2tte1.png","nsfw":false}],"prevPostId":"1phsohv","nextPostId":"1pibefp"}}