{"pageId":"/src/pages/posts/@id","routeParams":{"id":"1o7f176"},"data":{"post":{"date":1760544057000,"reddit":"https://www.reddit.com/r/touhou/comments/1o7f176","url":["https://i.redd.it/klxn6o5dtavf1.png"],"src":"https://x.com/simerike5/status/1978402414748201339","desc":"Yeah... Kaguya has definitely dragged Mokō back to Eientei before, at least to have Eirin check her out. Or maybe Eirin herself was the one who got to Mokō one way or another to confirm that the girl really is a Hōraian (or Hōrainese? What would be a good word for this? 🤔).\n\nAnd I kinda recall in FDS, it really felt like Mokō has been in-and-out of Eientei too? Like, not a regular, but definitely not just occasional.","artistId":"deetamu","characterIds":["kaguya","eirin"],"nsfw":false},"artist":{"id":"deetamu","name":"で～たむ","linkTwitter":"https://x.com/simerike5","linkPixiv":"https://www.pixiv.net/en/users/3079181","portrait":"portraits/artists/deetamu.webp","artworkCount":63,"characterCount":31},"characters":[{"id":"eirin","name":"Yagokoro Eirin","short_name":"Eirin","work":["in"],"portrait":"portraits/characters/eirin.webp","artworkCount":32,"artistCount":18},{"id":"kaguya","name":"Hōraisan Kaguya","short_name":"Kaguya","work":["in"],"portrait":"portraits/characters/kaguya.webp","artworkCount":44,"artistCount":19}],"randomArtistPosts":[{"id":"1h2l4mc","img":"https://i.redd.it/jjgw0bov7u3e1.png","nsfw":false},{"id":"1i0fo1j","img":"https://i.redd.it/u186hyngyrce1.png","nsfw":false},{"id":"1eyijyj","img":"https://i.redd.it/hno17i0wp7kd1.png","nsfw":false},{"id":"1pznk0s","img":"https://i.redd.it/y0oqbn2iidag1.png","nsfw":false}],"prevPostId":"1o750s9","nextPostId":"1o7rj2i"}}