{"pageId":"/src/pages/posts/@id","routeParams":{"id":"1gk73xb"},"data":{"post":{"date":1730814617000,"reddit":"https://www.reddit.com/r/touhou/comments/1gk73xb","url":["https://i.redd.it/eiv7l31h83zd1.png"],"src":"https://x.com/TYUMUKADE/status/1843335030434865284","desc":"I know it's a waste of a really big cake, Flan. But still, I think you might be overreacting a bit here. ","artistId":"chuumukade","characterIds":["flandre"],"nsfw":false},"artist":{"id":"chuumukade","name":"チュウムカデ","linkTwitter":"https://x.com/TYUMUKADE","linkPixiv":"https://www.pixiv.net/en/users/19115802","portrait":"portraits/artists/chuumukade.webp","artworkCount":55,"characterCount":53},"characters":[{"id":"flandre","name":"Flandre Scarlet","short_name":"Flandre","work":["eosd"],"portrait":"portraits/characters/flandre.webp","artworkCount":94,"artistCount":60}],"randomArtistPosts":[{"id":"1lgzxw5","img":"https://i.redd.it/gl9ugy5rza8f1.png","nsfw":false},{"id":"1ge19uw","img":"https://i.redd.it/i7w8ua36vhxd1.png","nsfw":false},{"id":"1eugxtk","img":"https://i.redd.it/p31v3iqp08jd1.png","nsfw":false},{"id":"1oe78o7","img":"https://i.redd.it/37y5d181xvwf1.png","nsfw":false}],"prevPostId":"1gk5wfg","nextPostId":"1gk8fv7"}}