{"pageId":"/src/pages/posts/@id","routeParams":{"id":"1m02vcw"},"data":{"post":{"date":1752537702000,"reddit":"https://www.reddit.com/r/touhou/comments/1m02vcw","url":["https://i.redd.it/u9t70h5dixcf1.png"],"src":"https://x.com/burijittou/status/1932285059358392591","desc":"Also known as \"KumoKumo\" – one \"kumo\" being cloud, the other \"kumo\" being spider.\n\nHuh... 🤨 Yukari's \"kumo\" in Yakumo is also cloud. So with this logic, ***Ichirin × Yukari*** might make more sense here. ~~Or we make it a ménage à trois with ***KumoKumoKumo***~~","artistId":"burijitou","characterIds":["yamame","ichirin"],"nsfw":false},"artist":{"id":"burijitou","name":"鰤十刀","linkTwitter":"https://x.com/burijittou","linkPixiv":"https://www.pixiv.net/en/users/134908","portrait":"portraits/placeholders/soldier.webp","artworkCount":4,"characterCount":6},"characters":[{"id":"yamame","name":"Kurodani Yamame","short_name":"Yamame","work":["sa"],"portrait":"portraits/characters/yamame.webp","artworkCount":11,"artistCount":8},{"id":"ichirin","name":"Kumoi Ichirin","short_name":"Ichirin","work":["ufo"],"portrait":"portraits/characters/ichirin.webp","artworkCount":11,"artistCount":10}],"randomArtistPosts":[{"id":"1imxuyk","img":"https://i.redd.it/rpjqiewdbiie1.png","nsfw":false},{"id":"1kr5ddz","img":"https://i.redd.it/qb9hxh18zx1f1.png","nsfw":false},{"id":"1lua8bd","img":"https://i.redd.it/s3rnxa1fkjbf1.png","nsfw":false}],"prevPostId":"1lzqcp0","nextPostId":"1m0bx90"}}