{"_urlRewrite":null,"pageId":"/src/pages/posts/@id","routeParams":{"id":"1gda6z1"},"data":{"post":{"date":1730033307000,"reddit":"https://www.reddit.com/r/touhou/comments/1gda6z1","url":["https://i.redd.it/pa4vbln8paxd1.png"],"src":"https://x.com/hidaruma_/status/1839590804312264735","desc":"Yes, my queen. 🗿 I will gladly stay late just for you.\n\nThe drink's so pure – either you'll probably won't sleep for the next couple of days, or it's distilled water.","artistId":"hidaruma","characterIds":["junko"],"nsfw":false},"artist":{"id":"hidaruma","name":"ヒダルマ","linkTwitter":"https://x.com/hidaruma_","linkPixiv":"https://www.pixiv.net/en/users/369449","portrait":"portraits/artists/hidaruma.webp","artworkCount":31,"characterCount":31},"characters":[{"id":"junko","name":"Junko","short_name":"Junko","work":["lolk"],"portrait":"portraits/characters/junko.webp","artworkCount":16,"artistCount":15}],"randomArtistPosts":[{"id":"1j5o794","img":"https://i.redd.it/zeepz5zav9ne1.png","nsfw":false},{"id":"1fp6ic5","img":"https://i.redd.it/kw3d55iazyqd1.png","nsfw":false},{"id":"1cgrug1","img":"https://i.redd.it/b90uarwh3mxc1.png","nsfw":false},{"id":"1g5q5a2","img":"https://i.redd.it/gn1nsfjucbvd1.png","nsfw":false}],"prevPostId":"1gcn2d2","nextPostId":"1gdcydb"}}