{"pageId":"/src/pages/posts/@id","routeParams":{"id":"1gpmi4q"},"data":{"post":{"date":1731423255000,"reddit":"https://www.reddit.com/r/touhou/comments/1gpmi4q","url":["https://i.redd.it/80ssk2k8ih0e1.png"],"src":"https://x.com/hua88331/status/1848357551672553778","desc":"Understood. Lemme load my save and come back with a higher level and better gear.","artistId":"ebi","characterIds":["flandre"],"nsfw":false},"artist":{"id":"ebi","name":"えび","linkTwitter":"https://x.com/hua88331","portrait":"portraits/artists/ebi.webp","artworkCount":27,"characterCount":6},"characters":[{"id":"flandre","name":"Flandre Scarlet","short_name":"Flandre","work":["eosd"],"portrait":"portraits/characters/flandre.webp","artworkCount":93,"artistCount":59}],"randomArtistPosts":[{"id":"1f074ri","img":"https://i.redd.it/raqocvd5lmkd1.png","nsfw":false},{"id":"1m4jf3g","img":"https://i.redd.it/ry7dkhwgkzdf1.png","nsfw":false},{"id":"1n1b0p8","img":"https://i.redd.it/39p9ms33rilf1.png","nsfw":false},{"id":"1g1blgo","img":"https://i.redd.it/044iabxe45ud1.png","nsfw":false}],"prevPostId":"1gpl88b","nextPostId":"1gqc6iq"}}