{"_urlRewrite":null,"pageId":"/src/pages/posts/@id","routeParams":{"id":"1hlf4vi"},"data":{"post":{"date":1735052079000,"reddit":"https://www.reddit.com/r/touhou/comments/1hlf4vi","url":["https://i.redd.it/49f5xeam8t8e1.png"],"src":"https://x.com/suwaneko2/status/1866815141968560599","desc":"I am an adherent to the idea that Remilia and Flandre are \"oni\", and thus are supernaturally very strong and very inclined towards physical activities.","artistId":"suwaneko","characterIds":["remilia"]},"artist":{"id":"suwaneko","name":"すわ猫","linkTwitter":"https://x.com/suwaneko10","linkPixiv":"https://www.pixiv.net/en/users/31855616","portrait":"/portraits/artists/suwaneko.webp","artworkCount":15,"characterCount":9},"characters":[{"id":"remilia","name":"Remilia Scarlet","short_name":"Remilia","work":["eosd"],"portrait":"/portraits/characters/remilia.webp","artworkCount":70,"artistCount":37}],"randomArtistPosts":[{"id":"1kd33aj","img":"https://i.redd.it/3n32ikh5vdye1.png"},{"id":"1jw04td","img":"https://i.redd.it/zlnlihq0w0ue1.png"},{"id":"1j77zsv","img":"https://i.redd.it/5hcknsd25one1.png"},{"id":"1ikml3d","img":"https://i.redd.it/3aw4nl8hwwhe1.png"}],"prevPostId":"1hleafg","nextPostId":"1hm0670"}}