{"pageId":"/src/pages/posts/@id","routeParams":{"id":"1p5xm40"},"data":{"post":{"date":1764029084000,"reddit":"https://www.reddit.com/r/touhou/comments/1p5xm40","url":["https://i.redd.it/7fwzxn05oa3g1.png"],"src":"https://x.com/flexible_B/status/1980565852455059651","desc":"Might be a good business to offer post danmaku fight cleanup 🤔 Reimu and Marisa probably leave lines and lines of craters and scorch marks in their wake when they resolve incidents.","artistId":"tog.","characterIds":["cirno","wriggle","yuuka","rumia"],"nsfw":false},"artist":{"id":"tog.","name":"tog.","linkTwitter":"https://x.com/flexible_B","linkPixiv":"https://www.pixiv.net/en/users/192808","portrait":"portraits/artists/tog..webp","artworkCount":16,"characterCount":33},"characters":[{"id":"rumia","name":"Rumia","short_name":"Rumia","work":["eosd"],"portrait":"portraits/characters/rumia.webp","artworkCount":34,"artistCount":23},{"id":"cirno","name":"Cirno","short_name":"Cirno","work":["eosd"],"portrait":"portraits/characters/cirno.webp","artworkCount":30,"artistCount":22},{"id":"wriggle","name":"Wriggle Nightbug","short_name":"Wriggle","work":["in"],"portrait":"portraits/characters/wriggle.webp","artworkCount":13,"artistCount":10},{"id":"yuuka","name":"Kazami Yūka","short_name":"Yūka","work":["pofv"],"portrait":"portraits/characters/yuuka.webp","artworkCount":14,"artistCount":10}],"randomArtistPosts":[{"id":"1ic1xsk","img":"https://i.redd.it/d3ch3uzpoqfe1.png","nsfw":false},{"id":"1op73hp","img":"https://i.redd.it/afkvwmcrqgzf1.png","nsfw":false},{"id":"1nngj0f","img":"https://i.redd.it/z5rdv8x0boqf1.png","nsfw":false},{"id":"1h4wqcw","img":"https://i.redd.it/6qp51s5j8g4e1.png","nsfw":false}],"prevPostId":"1p5kuby","nextPostId":"1p66tq9"}}