{"_urlRewrite":null,"pageId":"/src/pages/posts/@id","routeParams":{"id":"1k5zokn"},"data":{"post":{"date":1745416265000,"reddit":"https://www.reddit.com/r/touhou/comments/1k5zokn","url":["https://i.redd.it/qheorcdoalwe1.png"],"src":"https://x.com/OWATA12129/status/1904843324537594269","desc":"And her hips too, it seems...\n\nHmm... while [**Dai's sprite**](https://en.touhouwiki.net/wiki/Daiyousei) has feathers in *EoSD*, they seem to be missing in *GFW* ? The default for most artists seems to be the usual translucent wings. But wow – [**Risui's rendition**](https://en.touhouwiki.net/wiki/File:WOoHSDaiyousei.png) with the feathers looks really good.","artistId":"owata","characterIds":["daiyousei"]},"artist":{"id":"owata","name":"おわーー","linkTwitter":"https://x.com/OWATA12129","portrait":"portraits/placeholders/engineer.webp","artworkCount":2,"characterCount":2},"characters":[{"id":"daiyousei","name":"Daiyōsei","short_name":"Dai","work":["eosd"],"portrait":"portraits/characters/daiyousei.webp","artworkCount":5,"artistCount":5}],"randomArtistPosts":[{"id":"1jo56jc","img":"https://i.redd.it/8vsb3ddnh1se1.png"}],"prevPostId":"1k5yblp","nextPostId":"1k61kby"}}