{"pageId":"/src/pages/posts/@id","routeParams":{"id":"1qenj9y"},"data":{"post":{"date":1768587081000,"reddit":"https://www.reddit.com/r/touhou/comments/1qenj9y","url":["https://i.redd.it/sifl56yd5rdg1.png"],"src":"https://x.com/suwaneko2/status/1999809257148203502","desc":"See, Cirno tried taking off her ribbon, and it didn't do shit. 🤔","artistId":"suwaneko","characterIds":["rumia","cirno"],"nsfw":false},"artist":{"id":"suwaneko","name":"すわ猫","linkTwitter":"https://x.com/suwaneko10","linkPixiv":"https://www.pixiv.net/en/users/31855616","portrait":"portraits/artists/suwaneko.webp","artworkCount":25,"characterCount":14},"characters":[{"id":"rumia","name":"Rumia","short_name":"Rumia","work":["eosd"],"portrait":"portraits/characters/rumia.webp","artworkCount":34,"artistCount":23},{"id":"cirno","name":"Cirno","short_name":"Cirno","work":["eosd"],"portrait":"portraits/characters/cirno.webp","artworkCount":30,"artistCount":22}],"randomArtistPosts":[{"id":"1f0vnlx","img":"https://i.redd.it/9n241ppp4tkd1.png","nsfw":false},{"id":"1ou3sjq","img":"https://i.redd.it/0q5a31ex4l0g1.png","nsfw":false},{"id":"1p8pbus","img":"https://i.redd.it/c2jxnfbtfy3g1.png","nsfw":false},{"id":"1g51ia6","img":"https://i.redd.it/c6nxfa89v4vd1.png","nsfw":false}],"prevPostId":"1qemx3q","nextPostId":"1qfdwnn"}}