{"_urlRewrite":null,"pageId":"/src/pages/posts/@id","routeParams":{"id":"1joxgxn"},"data":{"post":{"date":1743518998000,"reddit":"https://www.reddit.com/r/touhou/comments/1joxgxn","url":["https://i.redd.it/k0zqerh4l8se1.png"],"src":"https://x.com/chanseele0128/status/1898279010813018364","desc":"Yeah, but we're going to prank Yūka. At least keep a low profile and your elegance at a minimum.","artistId":"seele","characterIds":["sakuya"],"nsfw":false},"artist":{"id":"seele","name":"Seele","linkTwitter":"https://x.com/chanseele0128","linkPixiv":"https://www.pixiv.net/en/users/16729214","portrait":"portraits/artists/seele.webp","artworkCount":22,"characterCount":14},"characters":[{"id":"sakuya","name":"Izayoi Sakuya","short_name":"Sakuya","work":["eosd"],"portrait":"portraits/characters/sakuya.webp","artworkCount":97,"artistCount":53}],"randomArtistPosts":[{"id":"1feblpd","img":"https://i.redd.it/g9x8bootx6od1.png","nsfw":false},{"id":"1i3i3q6","img":"https://i.redd.it/3entnsiiikde1.png","nsfw":false},{"id":"1dxfsp9","img":"https://i.redd.it/s2d0w4vlf3bd1.png","nsfw":false},{"id":"1cq73gw","img":"https://i.redd.it/znigta4urzzc1.png","nsfw":false}],"prevPostId":"1jow2xu","nextPostId":"1jpnsp9"}}