{"_urlRewrite":null,"pageId":"/src/pages/posts/@id","routeParams":{"id":"1bdqhru"},"data":{"post":{"date":1710333695000,"reddit":"https://www.reddit.com/r/touhou/comments/1bdqhru","url":["https://i.redd.it/54lcpeukj3oc1.png"],"src":"https://x.com/mendo_15___/status/1767423992774930543","desc":"When all the rabbits in the bamboo forest are part of the Udonge harem.","artistId":"mendou15","characterIds":["reisen"]},"artist":{"id":"mendou15","name":"めんどう１５","linkTwitter":"https://x.com/mendo_15___","linkPixiv":"https://www.pixiv.net/en/users/83944581","portrait":"/portraits/artists/mendou15.webp","artworkCount":17},"characters":[{"id":"reisen","name":"Reisen Udondein Inaba","short_name":"Reisen","work":["in"],"portrait":"/portraits/characters/reisen.webp","artworkCount":43}],"randomArtistPosts":[{"id":"1ho8cw1","img":"https://i.redd.it/g652ikv52m9e1.png"},{"id":"1eyla3l","img":"https://i.redd.it/w4mjxc3xa8kd1.png"},{"id":"1k6re9w","img":"https://i.redd.it/y9ugwbdr4swe1.png"},{"id":"1fb8rw5","img":"https://i.redd.it/4s3cy3p7iend1.png"}],"prevPostId":"1bb9ft5","nextPostId":"1bfcxrv"}}