{"pageId":"/src/pages/posts/@id","routeParams":{"id":"1nl7lsp"},"data":{"post":{"date":1758297816000,"reddit":"https://www.reddit.com/r/touhou/comments/1nl7lsp","url":["https://i.redd.it/02kta4z3a5qf1.png"],"src":"https://x.com/HeripanTomorrow/status/1960664544197665203","desc":"I just think that maybe you didn't need to shank them? 🤨 Ah, whatever. What flavor you want the ice cream, Koishi?","artistId":"sushirou","characterIds":["koishi"],"nsfw":false},"artist":{"id":"sushirou","name":"すしろう","linkTwitter":"https://x.com/HeripanTomorrow","linkPixiv":"https://www.pixiv.net/en/users/42276572","portrait":"portraits/artists/sushirou.webp","artworkCount":9,"characterCount":7},"characters":[{"id":"koishi","name":"Komeiji Koishi","short_name":"Koishi","work":["sa"],"portrait":"portraits/characters/koishi.webp","artworkCount":56,"artistCount":32}],"randomArtistPosts":[{"id":"1k9w09k","img":"https://i.redd.it/9b7fc8wyykxe1.png","nsfw":false},{"id":"1nsionf","img":"https://i.redd.it/k6kjlmoc4vrf1.png","nsfw":false},{"id":"1ihi225","img":"https://i.redd.it/jogqdk5bn4he1.png","nsfw":false},{"id":"1iw9eyi","img":"https://i.redd.it/1hegiyysxvke1.png","nsfw":false}],"prevPostId":"1nkxkr7","nextPostId":"1nllefk"}}