{"_urlRewrite":null,"pageId":"/src/pages/posts/@id","routeParams":{"id":"1npsk20"},"data":{"post":{"date":1758759706000,"reddit":"https://www.reddit.com/r/touhou/comments/1npsk20","url":["https://i.redd.it/w0ws7tokf7rf1.gif"],"src":"https://x.com/syope/status/1961346418029072645","desc":"Huh... while Enoko doesn't look it, she is still an immortal. And it seems we are supposed to look at her with the keyword **\"old\"** in mind. She's a contemporary of Zanmu... who just kinda hung around while immortal as a regular dog up until recently when she got her upgrade with that gem.\n\nOh, and this is a *Princess Mononoke* reference.","artistId":"shope","characterIds":["enoko"],"nsfw":false},"artist":{"id":"shope","name":"しょぺ","linkTwitter":"https://x.com/syope","linkPixiv":"https://www.pixiv.net/en/users/90634","portrait":"portraits/artists/shope.webp","artworkCount":6,"characterCount":10},"characters":[{"id":"enoko","name":"Mitsugashira Enoko","short_name":"Enoko","work":["udoalg"],"portrait":"portraits/characters/enoko.webp","artworkCount":4,"artistCount":4}],"randomArtistPosts":[{"id":"1l75z3g","img":"https://i.redd.it/7hvlz9k6uw5f1.png","nsfw":false},{"id":"1lc3t3a","img":"https://i.redd.it/6r14vj8h647f1.png","nsfw":false},{"id":"1lcwsaw","img":"https://i.redd.it/ijvtywhtbb7f1.png","nsfw":false},{"id":"1jl385z","img":"https://i.redd.it/euswe40yb8re1.png","nsfw":false}],"prevPostId":"1npg2ke","nextPostId":"1nq14rd"}}