{"_urlRewrite":null,"pageId":"/src/pages/posts/@id","routeParams":{"id":"1c30y8g"},"data":{"post":{"date":1713011776000,"reddit":"https://www.reddit.com/r/touhou/comments/1c30y8g","url":["https://i.redd.it/77vuolhgr8uc1.png"],"src":"https://x.com/simerike5/status/1779088132388045304","desc":"Yukari did a little trolling, to the audience.","artistId":"deetamu","characterIds":["yukari","merry"]},"artist":{"id":"deetamu","name":"で～たむ","linkTwitter":"https://x.com/simerike5","linkPixiv":"https://www.pixiv.net/en/users/3079181","portrait":"/portraits/artists/deetamu.webp","artworkCount":44,"characterCount":23},"characters":[{"id":"yukari","name":"Yakumo Yukari","short_name":"Yukari","work":["pcb","iamp","in","swr","sa","soku","aocf"],"portrait":"/portraits/characters/yukari.webp","artworkCount":40,"artistCount":29},{"id":"merry","name":"Maëlivérie Hearn","short_name":"Merry","work":["hifuu"],"portrait":"/portraits/characters/merry.webp","artworkCount":10,"artistCount":9}],"randomArtistPosts":[{"id":"1hu8kcj","img":"https://i.redd.it/4std4i9eu6be1.png"},{"id":"1lhbhez","img":"https://i.redd.it/75c5p6gimd8f1.png"},{"id":"1h2l4mc","img":"https://i.redd.it/jjgw0bov7u3e1.png"},{"id":"1ftq7bi","img":"https://i.redd.it/db829z53t5sd1.png"}],"prevPostId":"1c1dvpd","nextPostId":"1c3soxr"}}