{"pageId":"/src/pages/posts/@id","routeParams":{"id":"1paxo9n"},"data":{"post":{"date":1764547385000,"reddit":"https://www.reddit.com/r/touhou/comments/1paxo9n","url":["https://i.redd.it/8b1ck98bhh4g1.png"],"src":"https://www.pixiv.net/en/artworks/120698612","desc":"You know... I really like the image that Chimata is not average height, but actually short. 🤔 And when thinking about Chimata, the keyword Capitalism would come to mind, but I think she can be much more foundational than that? A market god. Trade. Transaction. Exchange of goods. This kind of thing transcends categorization of economy.\n\nAnd [**Chimata says that**](https://en.touhouwiki.net/wiki/Unconnected_Marketeers/Story/Sanae's_Scenario#:~:text=天狗風情) after Tsukasa whispered to her.","artistId":"iroiro_yaru_hito","characterIds":["chimata"],"nsfw":false},"artist":{"id":"iroiro_yaru_hito","name":"いろいろやる人","linkTwitter":"https://x.com/iro2do","linkPixiv":"https://www.pixiv.net/en/users/1341860","portrait":"portraits/artists/iroiro_yaru_hito.webp","artworkCount":20,"characterCount":26},"characters":[{"id":"chimata","name":"Tenkyū Chimata","short_name":"Chimata","work":["um"],"portrait":"portraits/characters/chimata.webp","artworkCount":16,"artistCount":13}],"randomArtistPosts":[{"id":"1pgxmvi","img":"https://i.redd.it/qvcbid4xev5g1.png","nsfw":false},{"id":"1p52qt6","img":"https://i.redd.it/qcd5f2bqn33g1.png","nsfw":false},{"id":"1gvox5v","img":"https://i.redd.it/tdwu7e94122e1.png","nsfw":false},{"id":"1ohuly5","img":"https://i.redd.it/5fcuyptdsqxf1.png","nsfw":false}],"prevPostId":"1palvmw","nextPostId":"1pb75ks"}}