{"_urlRewrite":null,"pageId":"/src/pages/posts/@id","routeParams":{"id":"1ln2b5k"},"data":{"post":{"date":1751159059000,"reddit":"https://www.reddit.com/r/touhou/comments/1ln2b5k","url":["https://i.redd.it/mefkmv6ymr9f1.png"],"src":"https://x.com/TYUMUKADE/status/1926676977529831433","desc":"Busty Yachie is certainly... huh. Not that rare, actually.","artistId":"chuumukade","characterIds":["yachie"],"nsfw":false},"artist":{"id":"chuumukade","name":"チュウムカデ","linkTwitter":"https://x.com/TYUMUKADE","linkPixiv":"https://www.pixiv.net/en/users/19115802","portrait":"portraits/artists/chuumukade.webp","artworkCount":51,"characterCount":50},"characters":[{"id":"yachie","name":"Kicchō Yachie","short_name":"Yachie","work":["wbawc","udoalg"],"portrait":"portraits/characters/yachie.webp","artworkCount":17,"artistCount":16}],"randomArtistPosts":[{"id":"1i8x22t","img":"https://i.redd.it/n04v37cvfyee1.png","nsfw":false},{"id":"1g6hbe8","img":"https://i.redd.it/n21pjhiohivd1.png","nsfw":false},{"id":"1f75xlb","img":"https://i.redd.it/gaoes8cj7emd1.png","nsfw":false},{"id":"1oe78o7","img":"https://i.redd.it/37y5d181xvwf1.png","nsfw":false}],"prevPostId":"1lmqb5z","nextPostId":"1ln9ath"}}