{"pageId":"/src/pages/posts/@id","routeParams":{"id":"1qdo0c3"},"data":{"post":{"date":1768494175000,"reddit":"https://www.reddit.com/r/touhou/comments/1qdo0c3","url":["https://i.redd.it/topm2wpzgjdg1.png"],"src":"https://x.com/jirufun/status/2011802087747940769","desc":"***EIRINNN. SEND REISEN OVER, PRONTO. AKYŪ FORGOT TO TAKE HER SUPPLEMENTS.***","artistId":"jiru","characterIds":["kosuzu"],"nsfw":false},"artist":{"id":"jiru","name":"じる","linkTwitter":"https://x.com/jirufun","linkPixiv":"https://www.pixiv.net/en/users/75677","portrait":"portraits/placeholders/spy.webp","artworkCount":16,"characterCount":23},"characters":[{"id":"kosuzu","name":"Motōri Kosuzu","short_name":"Kosuzu","work":["td"],"portrait":"portraits/characters/kosuzu.webp","artworkCount":13,"artistCount":11}],"randomArtistPosts":[{"id":"1m9gfkc","img":"https://i.redd.it/xknpuhcdc4ff1.png","nsfw":false},{"id":"1qcpy3e","img":"https://i.redd.it/7b35y6au0cdg1.png","nsfw":false},{"id":"1nkxkr7","img":"https://i.redd.it/3nqzlxc1w2qf1.png","nsfw":false},{"id":"1q4fvuy","img":"https://i.redd.it/5r3tsuojmhbg1.png","nsfw":false}],"prevPostId":"1qdnhb5","nextPostId":"1qekibx"}}