{"pageId":"/src/pages/posts/@id","routeParams":{"id":"1nsbth7"},"data":{"post":{"date":1759022800000,"reddit":"https://www.reddit.com/r/touhou/comments/1nsbth7","url":["https://i.redd.it/j3vivkuv5trf1.png"],"src":"https://x.com/mikadukimo777/status/1962478039897608640","desc":"Imagine another 文 book where Aya has Nareko host an actual quiz show, and we see the various characters reason their way through the choices they select.\n\nAnd the reference seems to be this game show called [**Time Shock?**](https://en.wikipedia.org/wiki/Time_Shock_(game_show))","artistId":"mikazukimo","characterIds":["cirno","nareko"],"nsfw":false},"artist":{"id":"mikazukimo","name":"ミカヅキモ","linkTwitter":"https://x.com/mikadukimo777","linkPixiv":"https://www.pixiv.net/en/users/8543340","portrait":"portraits/artists/mikazukimo.webp","artworkCount":27,"characterCount":38},"characters":[{"id":"cirno","name":"Cirno","short_name":"Cirno","work":["eosd"],"portrait":"portraits/characters/cirno.webp","artworkCount":29,"artistCount":22},{"id":"nareko","name":"Michigami Nareko","short_name":"Nareko","work":["fw"],"portrait":"portraits/characters/nareko.webp","artworkCount":28,"artistCount":21}],"randomArtistPosts":[{"id":"1jfqjws","img":"https://i.redd.it/rzwb17pdxupe1.png","nsfw":false},{"id":"1j0zxjk","img":"https://i.redd.it/v2fkr34n23me1.png","nsfw":false},{"id":"1d5m6z6","img":"https://i.redd.it/acal8o9shy3d1.png","nsfw":false},{"id":"1ll3wu1","img":"https://i.redd.it/uhfjfx1aoa9f1.png","nsfw":false}],"prevPostId":"1nryy3y","nextPostId":"1nsionf"}}