{"_urlRewrite":null,"pageId":"/src/pages/posts/@id","routeParams":{"id":"1f074ri"},"data":{"post":{"date":1724511192000,"reddit":"https://www.reddit.com/r/touhou/comments/1f074ri","url":["https://i.redd.it/raqocvd5lmkd1.png"],"src":"https://x.com/hua88331/status/1816757962222030895","desc":"Me and the boys escaping the larder, rolled a 1 and deadass ran straight into Remilia's study.","artistId":"ebi","characterIds":["sakuya","remilia"],"nsfw":false},"artist":{"id":"ebi","name":"えび","linkTwitter":"https://x.com/hua88331","portrait":"portraits/artists/ebi.webp","artworkCount":27,"characterCount":6},"characters":[{"id":"sakuya","name":"Izayoi Sakuya","short_name":"Sakuya","work":["eosd"],"portrait":"portraits/characters/sakuya.webp","artworkCount":90,"artistCount":51},{"id":"remilia","name":"Remilia Scarlet","short_name":"Remilia","work":["eosd"],"portrait":"portraits/characters/remilia.webp","artworkCount":104,"artistCount":51}],"randomArtistPosts":[{"id":"1n124i9","img":"https://i.redd.it/8rbtga0pdglf1.png","nsfw":false},{"id":"1n7is3l","img":"https://i.redd.it/tjci1a533zmf1.png","nsfw":false},{"id":"1gyt3iy","img":"https://i.redd.it/kpd7q6x78v2e1.png","nsfw":false},{"id":"1i6izbj","img":"https://i.redd.it/pndpupbkqcee1.png","nsfw":false}],"prevPostId":"1f04n3z","nextPostId":"1f0vnlx"}}