{"_urlRewrite":null,"pageId":"/src/pages/posts/@id","routeParams":{"id":"1k7k59t"},"data":{"post":{"date":1745585453000,"reddit":"https://www.reddit.com/r/touhou/comments/1k7k59t","url":["https://i.redd.it/khdk7iar9zwe1.png"],"src":"https://x.com/morishiey/status/1905460497274851704","desc":"Now I imagine the playable characters' cabinets to be filled with \"trophies\" from their encounters. Hell, imagine if Reimu still has Remilia's fang that broke off from the impact of a yin-yang orb landing on her face?\n\nCould be a nice feature to have for a compilation of Touhou games. It's a pretty interesting medium to slip in lore too.","artistId":"morisshi","characterIds":["aun"],"nsfw":false},"artist":{"id":"morisshi","name":"もりっしー","linkTwitter":"https://x.com/morishiey","linkPixiv":"https://www.pixiv.net/en/users/4590152","portrait":"portraits/placeholders/heavy.webp","artworkCount":3,"characterCount":4},"characters":[{"id":"aun","name":"Komano Aun","short_name":"Aun","work":["hsifs"],"portrait":"portraits/characters/aun.webp","artworkCount":20,"artistCount":17}],"randomArtistPosts":[{"id":"1nu7acl","img":"https://i.redd.it/tsi9pwh1e9sf1.png","nsfw":false},{"id":"1nryy3y","img":"https://i.redd.it/nbul380jdqrf1.png","nsfw":false}],"prevPostId":"1k6ufpp","nextPostId":"1k7ljtc"}}