{"_urlRewrite":null,"pageId":"/src/pages/posts/@id","routeParams":{"id":"1fmv7sx"},"data":{"post":{"date":1727017060000,"reddit":"https://www.reddit.com/r/touhou/comments/1fmv7sx","url":["https://i.redd.it/qcg1asqckdqd1.png"],"src":"https://x.com/simerike5/status/1837794812071928290","desc":"Are Sakuya's eyes dark blue, pale blue, or – much more recently – bright blue? 🤔","artistId":"deetamu","characterIds":["sakuya","remilia"]},"artist":{"id":"deetamu","name":"で～たむ","linkTwitter":"https://x.com/simerike5","linkPixiv":"https://www.pixiv.net/en/users/3079181","portrait":"/portraits/artists/deetamu.webp","artworkCount":41,"characterCount":22},"characters":[{"id":"sakuya","name":"Izayoi Sakuya","short_name":"Sakuya","work":["eosd"],"portrait":"/portraits/characters/sakuya.webp","artworkCount":58,"artistCount":37},{"id":"remilia","name":"Remilia Scarlet","short_name":"Remilia","work":["eosd"],"portrait":"/portraits/characters/remilia.webp","artworkCount":68,"artistCount":37}],"randomArtistPosts":[{"id":"1hbv5gf","img":"https://i.redd.it/zhjngct5g86e1.png"},{"id":"1h2l4mc","img":"https://i.redd.it/jjgw0bov7u3e1.png"},{"id":"1d1r7cg","img":"https://i.redd.it/ak20yn3xxy2d1.png"},{"id":"1ftq7bi","img":"https://i.redd.it/db829z53t5sd1.png"}],"prevPostId":"1fm4uru","nextPostId":"1fnmfp9"}}