{"_urlRewrite":null,"pageId":"/src/pages/posts/@id","routeParams":{"id":"1d73lrc"},"data":{"post":{"date":1717418941000,"reddit":"https://www.reddit.com/r/touhou/comments/1d73lrc","url":["https://i.redd.it/iljqirq7sc4d1.png"],"src":"https://x.com/Arachis_hypogae/status/1792322276370866485","desc":"When you weren't going to be home for a week, so you had your daughter stay over with her underground friend.","artistId":"yudepii","characterIds":["chen","orin"],"nsfw":false},"artist":{"id":"yudepii","name":"茹でピー","linkTwitter":"https://x.com/Arachis_hypogae","linkPixiv":"https://www.pixiv.net/en/users/264281","portrait":"portraits/placeholders/sniper.webp","artworkCount":1,"characterCount":2},"characters":[{"id":"chen","name":"Chen","short_name":"Chen","work":["pcb"],"portrait":"portraits/characters/chen.webp","artworkCount":31,"artistCount":20},{"id":"orin","name":"Kaenbyō Rin","short_name":"Orin","work":["sa","udoalg"],"portrait":"portraits/characters/orin.webp","artworkCount":36,"artistCount":23}],"randomArtistPosts":[],"prevPostId":"1d6cnae","nextPostId":"1d7wwk9"}}