{"_urlRewrite":null,"pageId":"/src/pages/posts/@id","routeParams":{"id":"1i9m97k"},"data":{"post":{"date":1737809366000,"reddit":"https://www.reddit.com/r/touhou/comments/1i9m97k","url":["https://i.redd.it/fas7si7ez4fe1.png"],"src":"https://x.com/Seachicken674/status/1878330229158223984","desc":"Okay, so \"**Urameshiya**\" is the Japanese \"Boo\" for ghosts. It's something along the line of \"I am vengeful\" or \"I have a grudge\" that ghosts stereotypically say when they show up in horror settings.","artistId":"chitose_hachi","characterIds":["kogasa","sanae"]},"artist":{"id":"chitose_hachi","name":"千歳はち","linkTwitter":"https://x.com/Seachicken674","linkPixiv":"https://www.pixiv.net/en/users/21620009","portrait":"portraits/artists/chitose_hachi.webp","artworkCount":11,"characterCount":20},"characters":[{"id":"sanae","name":"Kochiya Sanae","short_name":"Sanae","work":["mof","sa","ufo","soku","td","lolk","um","udoalg"],"portrait":"portraits/characters/sanae.webp","artworkCount":56,"artistCount":37},{"id":"kogasa","name":"Tatara Kogasa","short_name":"Kogasa","work":["ufo"],"portrait":"portraits/characters/kogasa.webp","artworkCount":14,"artistCount":12}],"randomArtistPosts":[{"id":"1jeyszo","img":"https://i.redd.it/4jl91hjntnpe1.png"},{"id":"1fnmu0h","img":"https://i.redd.it/hvnw6rczrkqd1.png"},{"id":"1m6if3t","img":"https://i.redd.it/5xzjj96magef1.png"},{"id":"1cnwq1x","img":"https://i.redd.it/8e21kfn8fezc1.png"}],"prevPostId":"1i8x22t","nextPostId":"1i9nfu8"}}